more.webassets-0.5.1-py3.5-nspkg.pth
more/webassets/.gitignore
more/webassets/__init__.py
more/webassets/core.py
more/webassets/directives.py
more/webassets/tweens.py
more/webassets/tests/conftest.py
more/webassets/tests/test_directives.py
more/webassets/tests/test_webassets.py
more/webassets/tests/fixtures/extra.css
more/webassets/tests/fixtures/extra.js
more/webassets/tests/fixtures/jquery.js
more/webassets/tests/fixtures/main.scss
more/webassets/tests/fixtures/underscore.js
more.webassets-0.5.1.dist-info/DESCRIPTION.rst
more.webassets-0.5.1.dist-info/METADATA
more.webassets-0.5.1.dist-info/RECORD
more.webassets-0.5.1.dist-info/WHEEL
more.webassets-0.5.1.dist-info/metadata.json
more.webassets-0.5.1.dist-info/namespace_packages.txt
more.webassets-0.5.1.dist-info/top_level.txt
