Metadata-Version: 2.0
Name: more.webassets
Version: 0.5.1
Summary: An opinionated Webassets integration for Morepath.
Home-page: http://github.com/morepath/more.webassets
Author: Seantis GmbH
Author-email: info@seantis.ch
License: BSD
Platform: any
Classifier: Intended Audience :: Developers
Classifier: Programming Language :: Python
Classifier: Programming Language :: Python :: 3
Classifier: Topic :: Software Development :: Libraries :: Python Modules
Classifier: License :: OSI Approved :: BSD License
Requires-Dist: morepath (>=0.16)
Requires-Dist: ordered-set
Requires-Dist: webassets
Requires-Dist: webob
Provides-Extra: test
Requires-Dist: coverage; extra == 'test'
Requires-Dist: pyscss; extra == 'test'
Requires-Dist: pytest; extra == 'test'
Requires-Dist: webtest; extra == 'test'
